bart_survival/__init__.py
bart_survival/simulation.py
bart_survival/surv_bart.py
bart_survival/version.py
bart_survival-0.1.1.dist-info/LICENSE
bart_survival-0.1.1.dist-info/METADATA
bart_survival-0.1.1.dist-info/WHEEL
bart_survival-0.1.1.dist-info/top_level.txt
bart_survival-0.1.1.dist-info/RECORD
