Metadata-Version: 2.1
Name: bart_survival
Version: 0.1.1
Summary: Survival analyses with Bayesian Additivie Regression Trees using PyMC-BART as BART backend.
Author-email: Jacob Tiegs <tiegsjacob@gmail.com>
Project-URL: Homepage, https://github.com/CDCgov/BART-Survival
License-File: LICENSE
Requires-Dist: numpy
Requires-Dist: scipy
Requires-Dist: pymc-bart
Requires-Dist: cloudpickle
Requires-Dist: pymc ; python_version <= "5.10.3"
